odoo/addons/sale_order_product_recommendation/README.rst
odoo/addons/sale_order_product_recommendation/__init__.py
odoo/addons/sale_order_product_recommendation/__manifest__.py
odoo/addons/sale_order_product_recommendation/i18n/es.po
odoo/addons/sale_order_product_recommendation/i18n/pt_BR.po
odoo/addons/sale_order_product_recommendation/i18n/sale_order_product_recommendation.pot
odoo/addons/sale_order_product_recommendation/models/__init__.py
odoo/addons/sale_order_product_recommendation/models/res_config_settings.py
odoo/addons/sale_order_product_recommendation/models/sale_order.py
odoo/addons/sale_order_product_recommendation/readme/CONFIGURE.rst
odoo/addons/sale_order_product_recommendation/readme/CONTRIBUTORS.rst
odoo/addons/sale_order_product_recommendation/readme/DESCRIPTION.rst
odoo/addons/sale_order_product_recommendation/readme/USAGE.rst
odoo/addons/sale_order_product_recommendation/static/description/icon.png
odoo/addons/sale_order_product_recommendation/static/description/index.html
odoo/addons/sale_order_product_recommendation/tests/__init__.py
odoo/addons/sale_order_product_recommendation/tests/test_recommendation.py
odoo/addons/sale_order_product_recommendation/tests/test_recommendation_common.py
odoo/addons/sale_order_product_recommendation/views/res_config_settings_views.xml
odoo/addons/sale_order_product_recommendation/views/sale_order_view.xml
odoo/addons/sale_order_product_recommendation/wizards/__init__.py
odoo/addons/sale_order_product_recommendation/wizards/sale_order_recommendation.py
odoo/addons/sale_order_product_recommendation/wizards/sale_order_recommendation_view.xml
odoo12_addon_sale_order_product_recommendation-12.0.3.0.2.dist-info/METADATA
odoo12_addon_sale_order_product_recommendation-12.0.3.0.2.dist-info/WHEEL
odoo12_addon_sale_order_product_recommendation-12.0.3.0.2.dist-info/top_level.txt
odoo12_addon_sale_order_product_recommendation-12.0.3.0.2.dist-info/RECORD
